myCalculatorPackage/__init__.py
myCalculatorPackage/division/__init__.py
myCalculatorPackage/division/divide.py
myCalculatorPackage/multiplication/__init__.py
myCalculatorPackage/multiplication/multiply.py
myCalculatorPackage6658-0.0.1.dist-info/LICENSE.txt
myCalculatorPackage6658-0.0.1.dist-info/METADATA
myCalculatorPackage6658-0.0.1.dist-info/WHEEL
myCalculatorPackage6658-0.0.1.dist-info/top_level.txt
myCalculatorPackage6658-0.0.1.dist-info/RECORD
